facecrop_thumb/__init__.py
facecrop_thumb/__main__.py
facecrop_thumb/face_detection.py
facecrop_thumb/image_processing.py
facecrop_thumb/main.py
facecrop_thumb/thumbnail_generation.py
facecrop_thumb/version.py
facecrop_thumb-1.0.5.dist-info/LICENSE
facecrop_thumb-1.0.5.dist-info/METADATA
facecrop_thumb-1.0.5.dist-info/WHEEL
facecrop_thumb-1.0.5.dist-info/entry_points.txt
facecrop_thumb-1.0.5.dist-info/top_level.txt
facecrop_thumb-1.0.5.dist-info/RECORD
