Metadata-Version: 2.1
Name: facecrop-thumb
Version: 1.0.5
Summary: Generate thumbnails of detected faces in images using Python.
Home-page: https://github.com/mr-vaibh/facecrop-thumb
Author: Vaibhav Shukla
Author-email: shuklavaibhav336@example.com
License: MIT
Keywords: face detection thumbnail image-processing
Classifier: Development Status :: 5 - Production/Stable
Classifier: Intended Audience :: Developers
Classifier: License :: OSI Approved :: MIT License
Classifier: Programming Language :: Python :: 3
License-File: LICENSE
Requires-Dist: mtcnn >=0.1.1
Requires-Dist: opencv-python >=4.9.0.80
